iamine/__init__.py
iamine/_version.py
iamine/api.py
iamine/config.py
iamine/core.py
iamine/exceptions.py
iamine/ia_mine.py
iamine/utils.py
iamine-0.1.6.dist-info/DESCRIPTION.rst
iamine-0.1.6.dist-info/entry_points.txt
iamine-0.1.6.dist-info/METADATA
iamine-0.1.6.dist-info/metadata.json
iamine-0.1.6.dist-info/RECORD
iamine-0.1.6.dist-info/top_level.txt
iamine-0.1.6.dist-info/WHEEL
