Metadata-Version: 2.0
Name: iamine
Version: 0.1.6
Summary: Concurrently retrieve metadata from Archive.org items.
Home-page: https://github.com/jjjake/iamine
Author: Jacob M. Johnson
Author-email: jake@archive.org
License: AGPL 3
Platform: UNKNOWN
Classifier: Development Status :: 1 - Planning
Classifier: Environment :: Console
Classifier: Intended Audience :: Developers
Classifier: License :: OSI Approved :: GNU Affero General Public License v3
Classifier: Natural Language :: English
Classifier: Programming Language :: Python :: 3
Requires-Dist: aiohttp (==0.13.1)
Requires-Dist: schema (==0.3.1)
Requires-Dist: docopt (==0.6.1)
